pytcc.cp37-win_amd64.pyd
pytcc-0.9.27.1.1.data/data/tcc-rtlib/gdi32.def
pytcc-0.9.27.1.1.data/data/tcc-rtlib/kernel32.def
pytcc-0.9.27.1.1.data/data/tcc-rtlib/libtcc1-64.a
pytcc-0.9.27.1.1.data/data/tcc-rtlib/msvcrt.def
pytcc-0.9.27.1.1.data/data/tcc-rtlib/user32.def
pytcc-0.9.27.1.1.data/data/tcc-rtlib/ws2_32.def
pytcc-0.9.27.1.1.data/data/tcc-rtlib/include/_mingw.h
pytcc-0.9.27.1.1.data/data/tcc-rtlib/include/assert.h
pytcc-0.9.27.1.1.data/data/tcc-rtlib/include/conio.h
pytcc-0.9.27.1.1.data/data/tcc-rtlib/include/ctype.h
pytcc-0.9.27.1.1.data/data/tcc-rtlib/include/dir.h
pytcc-0.9.27.1.1.data/data/tcc-rtlib/include/direct.h
pytcc-0.9.27.1.1.data/data/tcc-rtlib/include/dirent.h
pytcc-0.9.27.1.1.data/data/tcc-rtlib/include/dos.h
pytcc-0.9.27.1.1.data/data/tcc-rtlib/include/errno.h
pytcc-0.9.27.1.1.data/data/tcc-rtlib/include/excpt.h
pytcc-0.9.27.1.1.data/data/tcc-rtlib/include/fcntl.h
pytcc-0.9.27.1.1.data/data/tcc-rtlib/include/fenv.h
pytcc-0.9.27.1.1.data/data/tcc-rtlib/include/float.h
pytcc-0.9.27.1.1.data/data/tcc-rtlib/include/inttypes.h
pytcc-0.9.27.1.1.data/data/tcc-rtlib/include/io.h
pytcc-0.9.27.1.1.data/data/tcc-rtlib/include/iso646.h
pytcc-0.9.27.1.1.data/data/tcc-rtlib/include/limits.h
pytcc-0.9.27.1.1.data/data/tcc-rtlib/include/locale.h
pytcc-0.9.27.1.1.data/data/tcc-rtlib/include/malloc.h
pytcc-0.9.27.1.1.data/data/tcc-rtlib/include/math.h
pytcc-0.9.27.1.1.data/data/tcc-rtlib/include/mem.h
pytcc-0.9.27.1.1.data/data/tcc-rtlib/include/memory.h
pytcc-0.9.27.1.1.data/data/tcc-rtlib/include/process.h
pytcc-0.9.27.1.1.data/data/tcc-rtlib/include/setjmp.h
pytcc-0.9.27.1.1.data/data/tcc-rtlib/include/share.h
pytcc-0.9.27.1.1.data/data/tcc-rtlib/include/signal.h
pytcc-0.9.27.1.1.data/data/tcc-rtlib/include/stdalign.h
pytcc-0.9.27.1.1.data/data/tcc-rtlib/include/stdarg.h
pytcc-0.9.27.1.1.data/data/tcc-rtlib/include/stdbool.h
pytcc-0.9.27.1.1.data/data/tcc-rtlib/include/stddef.h
pytcc-0.9.27.1.1.data/data/tcc-rtlib/include/stdint.h
pytcc-0.9.27.1.1.dist-info/LICENCE
pytcc-0.9.27.1.1.dist-info/METADATA
pytcc-0.9.27.1.1.dist-info/WHEEL
pytcc-0.9.27.1.1.dist-info/top_level.txt
pytcc-0.9.27.1.1.dist-info/RECORD
