Metadata-Version: 2.1
Name: pytcc
Version: 0.9.27.1.1
Summary: A Python Wrapper for the API of the Tiny C Compiler (TCC)
Home-page: https://github.com/mrh1997/pytcc
Author: Robert Hölzl
Author-email: robert.hoelzl@posteo.de
Classifier: Development Status :: 3 - Alpha
Classifier: Operating System :: Microsoft :: Windows
Classifier: Operating System :: MacOS :: MacOS X
Classifier: Operating System :: POSIX :: Linux
Classifier: Intended Audience :: Developers
Classifier: License :: OSI Approved :: GNU General Public License v2 or later (GPLv2+)
Classifier: Programming Language :: Python
Classifier: Programming Language :: Python :: 3
Classifier: Programming Language :: Python :: 3.6
Classifier: Programming Language :: Python :: 3.7
Classifier: Programming Language :: Python :: 3.8
Classifier: Programming Language :: Python :: 3.9
Classifier: Programming Language :: Python :: 3.10
Classifier: Programming Language :: Python :: 3.11
Classifier: Programming Language :: C
Classifier: Topic :: Software Development :: Assemblers
Classifier: Topic :: Software Development :: Compilers
License-File: LICENCE
